ptychi/__init__.py
ptychi/device.py
ptychi/forward_models.py
ptychi/image_proc.py
ptychi/io_handles.py
ptychi/maps.py
ptychi/maths.py
ptychi/metrics.py
ptychi/position_correction.py
ptychi/propagate.py
ptychi/py.typed
ptychi/utils.py
ptychi/api/__init__.py
ptychi/api/enums.py
ptychi/api/task.py
ptychi/api/types.py
ptychi/api/options/__init__.py
ptychi/api/options/ad_general.py
ptychi/api/options/ad_ptychography.py
ptychi/api/options/base.py
ptychi/api/options/bh.py
ptychi/api/options/data.py
ptychi/api/options/dm.py
ptychi/api/options/lsqml.py
ptychi/api/options/pie.py
ptychi/api/options/plan.py
ptychi/api/options/task.py
ptychi/data_structures/__init__.py
ptychi/data_structures/base.py
ptychi/data_structures/object.py
ptychi/data_structures/opr_mode_weights.py
ptychi/data_structures/parameter_group.py
ptychi/data_structures/probe.py
ptychi/data_structures/probe_positions.py
ptychi/movies/__init__.py
ptychi/movies/api.py
ptychi/movies/io.py
ptychi/movies/mappings.py
ptychi/movies/movie_utils.py
ptychi/movies/settings.py
ptychi/reconstructors/__init__.py
ptychi/reconstructors/ad_general.py
ptychi/reconstructors/ad_ptychography.py
ptychi/reconstructors/base.py
ptychi/reconstructors/bh.py
ptychi/reconstructors/dm.py
ptychi/reconstructors/lsqml.py
ptychi/reconstructors/pie.py
ptychi/reconstructors/nn/__init__.py
ptychi/reconstructors/nn/components.py
ptychi/reconstructors/nn/models/autoencoder.py
ptychi/reconstructors/nn/models/unet.py
ptychi/timing/io.py
ptychi/timing/timer_utils.py
ptychi-1.1.0.dist-info/licenses/LICENSE.txt
ptychi-1.1.0.dist-info/METADATA
ptychi-1.1.0.dist-info/WHEEL
ptychi-1.1.0.dist-info/top_level.txt
ptychi-1.1.0.dist-info/RECORD
