Metadata-Version: 2.4
Name: ptychi
Version: 1.1.0
Summary: Pty-chi is a package of ptychography reconstruction engines
License: Apache License
Requires-Python: >=3.11
License-File: LICENSE.txt
Requires-Dist: h5py
Requires-Dist: matplotlib
Requires-Dist: mypy
Requires-Dist: numpy
Requires-Dist: pandas
Requires-Dist: ruff
Requires-Dist: scikit-image
Requires-Dist: scikit-learn
Requires-Dist: scipy
Requires-Dist: torch>=2.4.1
Requires-Dist: torchvision
Requires-Dist: tqdm
Provides-Extra: movies
Requires-Dist: opencv-python; extra == "movies"
Dynamic: license-file
